dccl/__init__.py
dccl-0.0.2.dist-info/LICENSE
dccl-0.0.2.dist-info/METADATA
dccl-0.0.2.dist-info/WHEEL
dccl-0.0.2.dist-info/top_level.txt
dccl-0.0.2.dist-info/RECORD
