Metadata-Version: 2.1
Name: dccl
Version: 0.0.2
Summary: Connect to any DCC tool from anywhere.
Home-page: https://github.com/coreprocess/dccl/dccl
Author: Niklas Salmoukas
Author-email: niklas@salmoukas.com
License: LGPLv3
Platform: UNKNOWN
Classifier: Programming Language :: Python :: 3
Classifier: License :: OSI Approved :: GNU Lesser General Public License v3 (LGPLv3)
Classifier: Operating System :: OS Independent
Requires-Python: >=3.6
